CHANGELOG.md
MANIFEST.in
README.md
setup.py
timekiller.py
timekiller.egg-info/PKG-INFO
timekiller.egg-info/SOURCES.txt
timekiller.egg-info/dependency_links.txt
timekiller.egg-info/not-zip-safe
timekiller.egg-info/top_level.txt