Metadata-Version: 1.1
Name: timekiller
Version: 0.0.3
Summary: It lets call any function with a timeout
Home-page: https://github.com/GlobalStudioES/timekiller
Author: Alberto Galera Jimenez
Author-email: agalera@globalstudio.es
License: MIT
Keywords: timekiller
Platform: UNKNOWN
Classifier: Development Status :: 4 - Beta
Classifier: Topic :: Software Development :: Libraries :: Python Modules
Classifier: Intended Audience :: Developers
Classifier: License :: OSI Approved :: GNU General Public License (GPL)
Classifier: Natural Language :: English
Classifier: Programming Language :: Python :: 2
Classifier: Programming Language :: Python :: 2.6
Classifier: Programming Language :: Python :: 2.7
Classifier: Programming Language :: Python :: 3
Classifier: Programming Language :: Python :: 3.3
Classifier: Programming Language :: Python :: 3.4
Classifier: Programming Language :: Python :: 3.5
